[
    {
        "orderId":  "20635111",
        "salesOrder":  "SO106371",
        "fundId":  "175124",
        "fundname":  "Snap!Store Customer",
        "placedDate":  "2/3/2024 4:35 pm",
        "logoScript":  null,
        "priColor":  null,
        "secColor":  null,
        "logoId":  null,
        "digital":  1,
        "digiSmall":  null
    },
    {
        "orderId":  "20635195",
        "salesOrder":  "SO106372",
        "fundId":  "181358",
        "fundname":  "Snap!Store Customer",
        "placedDate":  "2/3/2024 4:36 pm",
        "logoScript":  null,
        "priColor":  null,
        "secColor":  null,
        "logoId":  null,
        "digital":  1,
        "digiSmall":  null
    },
    {
        "orderId":  "20637007",
        "salesOrder":  "SO106374",
        "fundId":  "208549",
        "fundname":  "Snap!Store Customer",
        "placedDate":  "2/4/2024 12:32 am",
        "logoScript":  null,
        "priColor":  null,
        "secColor":  null,
        "logoId":  null,
        "digital":  4,
        "digiSmall":  null
    },
    {
        "orderId":  "20637009",
        "salesOrder":  "SO106375",
        "fundId":  "183548",
        "fundname":  "Snap!Store Customer",
        "placedDate":  "2/4/2024 12:32 am",
        "logoScript":  null,
        "priColor":  null,
        "secColor":  null,
        "logoId":  null,
        "digital":  1,
        "digiSmall":  null
    },
    {
        "orderId":  "20639351",
        "salesOrder":  "SO106376",
        "fundId":  "204115",
        "fundname":  "Snap!Store Customer",
        "placedDate":  "2/4/2024 8:30 am",
        "logoScript":  null,
        "priColor":  null,
        "secColor":  null,
        "logoId":  null,
        "digital":  4,
        "digiSmall":  null
    },
    {
        "orderId":  "20642829",
        "salesOrder":  "SO106378",
        "fundId":  "181079",
        "fundname":  "Snap!Store Customer",
        "placedDate":  "2/4/2024 4:32 pm",
        "logoScript":  null,
        "priColor":  null,
        "secColor":  null,
        "logoId":  null,
        "digital":  null,
        "digiSmall":  2
    },
    {
        "orderId":  "20642831",
        "salesOrder":  "SO106379",
        "fundId":  "205567",
        "fundname":  "Snap!Store Customer",
        "placedDate":  "2/4/2024 4:32 pm",
        "logoScript":  null,
        "priColor":  null,
        "secColor":  null,
        "logoId":  null,
        "digital":  2,
        "digiSmall":  null
    },
    {
        "orderId":  "20642834",
        "salesOrder":  "SO106380",
        "fundId":  "206153",
        "fundname":  "Snap!Store Customer",
        "placedDate":  "2/4/2024 4:32 pm",
        "logoScript":  null,
        "priColor":  null,
        "secColor":  null,
        "logoId":  null,
        "digital":  1,
        "digiSmall":  null
    },
    {
        "orderId":  "20642839",
        "salesOrder":  "SO106381",
        "fundId":  "196822",
        "fundname":  "Snap!Store Customer",
        "placedDate":  "2/4/2024 4:33 pm",
        "logoScript":  null,
        "priColor":  null,
        "secColor":  null,
        "logoId":  null,
        "digital":  4,
        "digiSmall":  null
    },
    {
        "orderId":  "20642844",
        "salesOrder":  "SO106383",
        "fundId":  "171013",
        "fundname":  "Snap!Store Customer",
        "placedDate":  "2/4/2024 4:33 pm",
        "logoScript":  null,
        "priColor":  null,
        "secColor":  null,
        "logoId":  null,
        "digital":  null,
        "digiSmall":  1
    },
    {
        "orderId":  "20642847",
        "salesOrder":  "SO106384",
        "fundId":  "206558",
        "fundname":  "Snap!Store Customer",
        "placedDate":  "2/4/2024 4:34 pm",
        "logoScript":  null,
        "priColor":  null,
        "secColor":  null,
        "logoId":  null,
        "digital":  1,
        "digiSmall":  2
    },
    {
        "orderId":  "20642850",
        "salesOrder":  "SO106385",
        "fundId":  "183693",
        "fundname":  "Snap!Store Customer",
        "placedDate":  "2/4/2024 4:34 pm",
        "logoScript":  null,
        "priColor":  null,
        "secColor":  null,
        "logoId":  null,
        "digital":  2,
        "digiSmall":  null
    },
    {
        "orderId":  "20642853",
        "salesOrder":  "SO106386",
        "fundId":  "196624",
        "fundname":  "Snap!Store Customer",
        "placedDate":  "2/4/2024 4:35 pm",
        "logoScript":  null,
        "priColor":  null,
        "secColor":  null,
        "logoId":  null,
        "digital":  3,
        "digiSmall":  2
    },
    {
        "orderId":  "20642858",
        "salesOrder":  "SO106387",
        "fundId":  "182109",
        "fundname":  "Snap!Store Customer",
        "placedDate":  "2/4/2024 4:35 pm",
        "logoScript":  null,
        "priColor":  null,
        "secColor":  null,
        "logoId":  null,
        "digital":  2,
        "digiSmall":  1
    },
    {
        "orderId":  "20642860",
        "salesOrder":  "SO106388",
        "fundId":  "206253",
        "fundname":  "Snap!Store Customer",
        "placedDate":  "2/4/2024 4:35 pm",
        "logoScript":  null,
        "priColor":  null,
        "secColor":  null,
        "logoId":  null,
        "digital":  2,
        "digiSmall":  4
    },
    {
        "orderId":  "20642894",
        "salesOrder":  "SO106377",
        "fundId":  "181926",
        "fundname":  "Snap!Store Customer",
        "placedDate":  "2/4/2024 4:31 pm",
        "logoScript":  null,
        "priColor":  null,
        "secColor":  null,
        "logoId":  null,
        "digital":  8,
        "digiSmall":  null
    },
    {
        "orderId":  "20647293",
        "salesOrder":  "SO106389",
        "fundId":  "176515",
        "fundname":  "Snap!Store Customer",
        "placedDate":  "2/5/2024 12:30 am",
        "logoScript":  null,
        "priColor":  null,
        "secColor":  null,
        "logoId":  null,
        "digital":  1,
        "digiSmall":  null
    },
    {
        "orderId":  "20647295",
        "salesOrder":  "SO106390",
        "fundId":  "181921",
        "fundname":  "Snap!Store Customer",
        "placedDate":  "2/5/2024 12:31 am",
        "logoScript":  null,
        "priColor":  null,
        "secColor":  null,
        "logoId":  null,
        "digital":  null,
        "digiSmall":  1
    },
    {
        "orderId":  "20647297",
        "salesOrder":  "SO106391",
        "fundId":  "183438",
        "fundname":  "Snap!Store Customer",
        "placedDate":  "2/5/2024 12:31 am",
        "logoScript":  null,
        "priColor":  null,
        "secColor":  null,
        "logoId":  null,
        "digital":  1,
        "digiSmall":  1
    },
    {
        "orderId":  "20651883",
        "salesOrder":  "SO106393",
        "fundId":  "181679",
        "fundname":  "Snap!Store Customer",
        "placedDate":  "2/5/2024 8:30 am",
        "logoScript":  null,
        "priColor":  null,
        "secColor":  null,
        "logoId":  null,
        "digital":  2,
        "digiSmall":  null
    }
]
